{
  "experiment": "exp3",
  "condition": {
    "num_classes": 5,
    "class_list": [
      1,
      2,
      3,
      5,
      9
    ],
    "class_names": [
      "Trouser",
      "Pullover",
      "Dress",
      "Sandal",
      "Ankle boot"
    ],
    "combo_idx": 4,
    "subset_pct": 40,
    "num_samples": 12000,
    "samples_per_class": 2400,
    "train_samples": 10800,
    "val_samples": 1200,
    "test_samples": 5000
  },
  "seed": 31380194,
  "timestamp": "2026-01-17T23:18:02.704399",
  "training_dynamics": {
    "epochs_trained": 16,
    "best_epoch": 6,
    "best_val_accuracy": 0.9858333333333333,
    "final_train_loss": 0.012069669346784561,
    "final_val_loss": 0.07052840782484661,
    "training_time_seconds": 8.298450708389282
  },
  "training_history": {
    "train_loss": [
      0.15586944509121264,
      0.07540238038058111,
      0.056571174412965775,
      0.045522545199819214,
      0.03414189744535448,
      0.02848957982479137,
      0.02438734865026857,
      0.024097939864002146,
      0.02133536553261774,
      0.015079243438631453,
      0.009206691723952026,
      0.006724934773148949,
      0.009661309184895219,
      0.014373974443353732,
      0.008948222481829566,
      0.012069669346784561
    ],
    "val_loss": [
      0.08869904731710752,
      0.05777320181330045,
      0.058811196001867454,
      0.06197567825516065,
      0.06978713644047578,
      0.05494055476039648,
      0.058186693526804445,
      0.06481231065467,
      0.057089200106759865,
      0.06225386386116346,
      0.0714437786117196,
      0.06399077900142099,
      0.07083283767725031,
      0.06900501366471871,
      0.10235193135216832,
      0.07052840782484661
    ],
    "val_accuracy": [
      0.97,
      0.98,
      0.9775,
      0.9766666666666667,
      0.975,
      0.9791666666666666,
      0.9816666666666667,
      0.98,
      0.9791666666666666,
      0.9833333333333333,
      0.9791666666666666,
      0.985,
      0.9816666666666667,
      0.9808333333333333,
      0.97,
      0.9858333333333333
    ]
  },
  "global_metrics": {
    "accuracy": 0.9832,
    "balanced_accuracy": 0.9831999999999999,
    "top_3_accuracy": 0.9998,
    "top_5_accuracy": 1.0,
    "log_loss": 0.05348578736335059,
    "mcc": 0.9790143426651807,
    "cohens_kappa": 0.979,
    "precision_macro": 0.983293223854945,
    "precision_micro": 0.9832,
    "precision_weighted": 0.9832932238549449,
    "recall_macro": 0.9831999999999999,
    "recall_micro": 0.9832,
    "recall_weighted": 0.9832,
    "f1_macro": 0.9832175997260022,
    "f1_micro": 0.9832,
    "f1_weighted": 0.9832175997260021,
    "auroc_macro": 0.999435675,
    "auroc_weighted": 0.9994356750000001,
    "auprc_macro": 0.9978010697443278
  },
  "per_class_metrics": {
    "0": {
      "precision": 0.9928571428571429,
      "recall": 0.973,
      "f1": 0.9828282828282828,
      "specificity": 0.99825,
      "fpr": 0.00175,
      "fnr": 0.027,
      "auroc": 0.9996407500000001,
      "auprc": 0.9989008229831977,
      "support": 1000,
      "tp": 973,
      "tn": 3993,
      "fp": 7,
      "fn": 27
    },
    "1": {
      "precision": 0.9751984126984127,
      "recall": 0.983,
      "f1": 0.9790836653386453,
      "specificity": 0.99375,
      "fpr": 0.00625,
      "fnr": 0.017,
      "auroc": 0.999247625,
      "auprc": 0.997452883644884,
      "support": 1000,
      "tp": 983,
      "tn": 3975,
      "fp": 25,
      "fn": 17
    },
    "2": {
      "precision": 0.963402571711177,
      "recall": 0.974,
      "f1": 0.9686723023371456,
      "specificity": 0.99075,
      "fpr": 0.00925,
      "fnr": 0.026,
      "auroc": 0.9985919999999999,
      "auprc": 0.9937520213512877,
      "support": 1000,
      "tp": 974,
      "tn": 3963,
      "fp": 37,
      "fn": 26
    },
    "3": {
      "precision": 0.9920079920079921,
      "recall": 0.993,
      "f1": 0.9925037481259369,
      "specificity": 0.998,
      "fpr": 0.002,
      "fnr": 0.007,
      "auroc": 0.99987575,
      "auprc": 0.9994711878665178,
      "support": 1000,
      "tp": 993,
      "tn": 3992,
      "fp": 8,
      "fn": 7
    },
    "4": {
      "precision": 0.993,
      "recall": 0.993,
      "f1": 0.993,
      "specificity": 0.99825,
      "fpr": 0.00175,
      "fnr": 0.007,
      "auroc": 0.99982225,
      "auprc": 0.9994284328757516,
      "support": 1000,
      "tp": 993,
      "tn": 3993,
      "fp": 7,
      "fn": 7
    }
  },
  "confusion_matrix": [
    [
      973,
      5,
      22,
      0,
      0
    ],
    [
      0,
      983,
      15,
      2,
      0
    ],
    [
      7,
      19,
      974,
      0,
      0
    ],
    [
      0,
      0,
      0,
      993,
      7
    ],
    [
      0,
      1,
      0,
      6,
      993
    ]
  ]
}