{
  "experiment": "exp3",
  "condition": {
    "num_classes": 6,
    "class_list": [
      0,
      1,
      3,
      4,
      6,
      8
    ],
    "class_names": [
      "T-shirt/top",
      "Trouser",
      "Dress",
      "Coat",
      "Shirt",
      "Bag"
    ],
    "combo_idx": 1,
    "subset_pct": 40,
    "num_samples": 14400,
    "samples_per_class": 2400,
    "train_samples": 12960,
    "val_samples": 1440,
    "test_samples": 6000
  },
  "seed": 73962792,
  "timestamp": "2026-01-18T00:59:51.378368",
  "training_dynamics": {
    "epochs_trained": 14,
    "best_epoch": 4,
    "best_val_accuracy": 0.89375,
    "final_train_loss": 0.056358799071101646,
    "final_val_loss": 0.41017802324559954,
    "training_time_seconds": 8.289061546325684
  },
  "training_history": {
    "train_loss": [
      0.5151697754713115,
      0.33317513272092847,
      0.2909330478295904,
      0.25512232792935347,
      0.21756555925449128,
      0.19007302629830214,
      0.16610868631178521,
      0.14495419056654857,
      0.12616576629649537,
      0.10447622800310111,
      0.09071635034192226,
      0.08443595675448773,
      0.07029620247659057,
      0.056358799071101646
    ],
    "val_loss": [
      0.3784173965454102,
      0.3380774113867018,
      0.31405101550949943,
      0.3048189785745409,
      0.32155948678652446,
      0.30934506720966765,
      0.3319989826944139,
      0.3291950129800373,
      0.33180500004026625,
      0.35790826148457,
      0.3590551972389221,
      0.37951903922690283,
      0.35656062447362474,
      0.41017802324559954
    ],
    "val_accuracy": [
      0.8631944444444445,
      0.8708333333333333,
      0.8902777777777777,
      0.8854166666666666,
      0.8680555555555556,
      0.8854166666666666,
      0.8826388888888889,
      0.8868055555555555,
      0.8847222222222222,
      0.89375,
      0.8861111111111111,
      0.8868055555555555,
      0.8840277777777777,
      0.8854166666666666
    ]
  },
  "global_metrics": {
    "accuracy": 0.887,
    "balanced_accuracy": 0.887,
    "top_3_accuracy": 0.9913333333333333,
    "top_5_accuracy": 0.9996666666666667,
    "log_loss": 0.3011802803437187,
    "mcc": 0.8645271813032427,
    "cohens_kappa": 0.8644000000000001,
    "precision_macro": 0.8869516055780231,
    "precision_micro": 0.887,
    "precision_weighted": 0.886951605578023,
    "recall_macro": 0.887,
    "recall_micro": 0.887,
    "recall_weighted": 0.887,
    "f1_macro": 0.8866457762930255,
    "f1_micro": 0.887,
    "f1_weighted": 0.8866457762930257,
    "auroc_macro": 0.9867773333333334,
    "auroc_weighted": 0.9867773333333333,
    "auprc_macro": 0.9474664302427156
  },
  "per_class_metrics": {
    "0": {
      "precision": 0.8672839506172839,
      "recall": 0.843,
      "f1": 0.8549695740365111,
      "specificity": 0.9742,
      "fpr": 0.0258,
      "fnr": 0.157,
      "auroc": 0.9830979999999999,
      "auprc": 0.925128913269162,
      "support": 1000,
      "tp": 843,
      "tn": 4871,
      "fp": 129,
      "fn": 157
    },
    "1": {
      "precision": 0.9889224572004028,
      "recall": 0.982,
      "f1": 0.985449071751129,
      "specificity": 0.9978,
      "fpr": 0.0022,
      "fnr": 0.018,
      "auroc": 0.9993338,
      "auprc": 0.9976850056268544,
      "support": 1000,
      "tp": 982,
      "tn": 4989,
      "fp": 11,
      "fn": 18
    },
    "2": {
      "precision": 0.9206680584551148,
      "recall": 0.882,
      "f1": 0.9009193054136875,
      "specificity": 0.9848,
      "fpr": 0.0152,
      "fnr": 0.118,
      "auroc": 0.992795,
      "auprc": 0.9659784559375107,
      "support": 1000,
      "tp": 882,
      "tn": 4924,
      "fp": 76,
      "fn": 118
    },
    "3": {
      "precision": 0.8708375378405651,
      "recall": 0.863,
      "f1": 0.8669010547463586,
      "specificity": 0.9744,
      "fpr": 0.0256,
      "fnr": 0.137,
      "auroc": 0.9896498,
      "auprc": 0.950992459373154,
      "support": 1000,
      "tp": 863,
      "tn": 4872,
      "fp": 128,
      "fn": 137
    },
    "4": {
      "precision": 0.7509920634920635,
      "recall": 0.757,
      "f1": 0.7539840637450199,
      "specificity": 0.9498,
      "fpr": 0.0502,
      "fnr": 0.243,
      "auroc": 0.9561881999999999,
      "auprc": 0.8468653711798304,
      "support": 1000,
      "tp": 757,
      "tn": 4749,
      "fp": 251,
      "fn": 243
    },
    "5": {
      "precision": 0.9230055658627088,
      "recall": 0.995,
      "f1": 0.9576515880654476,
      "specificity": 0.9834,
      "fpr": 0.0166,
      "fnr": 0.005,
      "auroc": 0.9995992,
      "auprc": 0.9981483760697824,
      "support": 1000,
      "tp": 995,
      "tn": 4917,
      "fp": 83,
      "fn": 5
    }
  },
  "confusion_matrix": [
    [
      843,
      1,
      13,
      3,
      113,
      27
    ],
    [
      0,
      982,
      14,
      2,
      0,
      2
    ],
    [
      21,
      6,
      882,
      45,
      33,
      13
    ],
    [
      0,
      1,
      24,
      863,
      105,
      7
    ],
    [
      107,
      1,
      24,
      77,
      757,
      34
    ],
    [
      1,
      2,
      1,
      1,
      0,
      995
    ]
  ]
}