{
  "experiment": "exp3",
  "condition": {
    "num_classes": 8,
    "class_list": [
      1,
      2,
      4,
      5,
      6,
      7,
      8,
      9
    ],
    "class_names": [
      "Trouser",
      "Pullover",
      "Coat",
      "Sandal",
      "Shirt",
      "Sneaker",
      "Bag",
      "Ankle boot"
    ],
    "combo_idx": 4,
    "subset_pct": 80,
    "num_samples": 38400,
    "samples_per_class": 4800,
    "train_samples": 34560,
    "val_samples": 3840,
    "test_samples": 8000
  },
  "seed": 14994796,
  "timestamp": "2026-01-17T20:44:10.528702",
  "training_dynamics": {
    "epochs_trained": 13,
    "best_epoch": 3,
    "best_val_accuracy": 0.9440104166666666,
    "final_train_loss": 0.057465834465067554,
    "final_val_loss": 0.21947033936157823,
    "training_time_seconds": 21.444971799850464
  },
  "training_history": {
    "train_loss": [
      0.3742690576447381,
      0.22160059933861095,
      0.18110311073423535,
      0.15601477687833487,
      0.1377950620458082,
      0.11872387526004954,
      0.10782461766567496,
      0.09627527409595334,
      0.08656473283104046,
      0.07557178561110049,
      0.06704211281267582,
      0.06064761366815893,
      0.057465834465067554
    ],
    "val_loss": [
      0.2941688137749831,
      0.18037669186790783,
      0.1678610224276781,
      0.21457584152619044,
      0.1874288969983657,
      0.16869049835950137,
      0.1778697882158061,
      0.18388037799547116,
      0.18527056310946743,
      0.18467144841949146,
      0.2053776519993941,
      0.22386054910408953,
      0.21947033936157823
    ],
    "val_accuracy": [
      0.8901041666666667,
      0.9341145833333333,
      0.9359375,
      0.9244791666666666,
      0.9388020833333334,
      0.9424479166666667,
      0.9393229166666667,
      0.9375,
      0.9440104166666666,
      0.9434895833333333,
      0.9375,
      0.9424479166666667,
      0.9421875
    ]
  },
  "global_metrics": {
    "accuracy": 0.932875,
    "balanced_accuracy": 0.932875,
    "top_3_accuracy": 0.997625,
    "top_5_accuracy": 0.999875,
    "log_loss": 0.17927188415536852,
    "mcc": 0.9234360487196475,
    "cohens_kappa": 0.9232857142857143,
    "precision_macro": 0.9332312205023934,
    "precision_micro": 0.932875,
    "precision_weighted": 0.9332312205023934,
    "recall_macro": 0.932875,
    "recall_micro": 0.932875,
    "recall_weighted": 0.932875,
    "f1_macro": 0.9325256990547618,
    "f1_micro": 0.932875,
    "f1_weighted": 0.9325256990547617,
    "auroc_macro": 0.99622275,
    "auroc_weighted": 0.99622275,
    "auprc_macro": 0.9771909411322073
  },
  "per_class_metrics": {
    "0": {
      "precision": 0.991991991991992,
      "recall": 0.991,
      "f1": 0.991495747873937,
      "specificity": 0.9988571428571429,
      "fpr": 0.001142857142857143,
      "fnr": 0.009,
      "auroc": 0.9999564285714285,
      "auprc": 0.9997042910923525,
      "support": 1000,
      "tp": 991,
      "tn": 6992,
      "fp": 8,
      "fn": 9
    },
    "1": {
      "precision": 0.8529130850047756,
      "recall": 0.893,
      "f1": 0.8724963361016123,
      "specificity": 0.978,
      "fpr": 0.022,
      "fnr": 0.107,
      "auroc": 0.9917600000000001,
      "auprc": 0.950670341609587,
      "support": 1000,
      "tp": 893,
      "tn": 6846,
      "fp": 154,
      "fn": 107
    },
    "2": {
      "precision": 0.8526315789473684,
      "recall": 0.891,
      "f1": 0.8713936430317849,
      "specificity": 0.978,
      "fpr": 0.022,
      "fnr": 0.109,
      "auroc": 0.9919337142857143,
      "auprc": 0.9454212441894368,
      "support": 1000,
      "tp": 891,
      "tn": 6846,
      "fp": 154,
      "fn": 109
    },
    "3": {
      "precision": 0.9733464955577492,
      "recall": 0.986,
      "f1": 0.9796323894684551,
      "specificity": 0.9961428571428571,
      "fpr": 0.003857142857142857,
      "fnr": 0.014,
      "auroc": 0.9997469999999998,
      "auprc": 0.998197830435227,
      "support": 1000,
      "tp": 986,
      "tn": 6973,
      "fp": 27,
      "fn": 14
    },
    "4": {
      "precision": 0.8985343855693348,
      "recall": 0.797,
      "f1": 0.8447270800211977,
      "specificity": 0.9871428571428571,
      "fpr": 0.012857142857142857,
      "fnr": 0.203,
      "auroc": 0.988518,
      "auprc": 0.9366930069311287,
      "support": 1000,
      "tp": 797,
      "tn": 6910,
      "fp": 90,
      "fn": 203
    },
    "5": {
      "precision": 0.9672466734902764,
      "recall": 0.945,
      "f1": 0.9559939301972686,
      "specificity": 0.9954285714285714,
      "fpr": 0.004571428571428572,
      "fnr": 0.055,
      "auroc": 0.9989997142857143,
      "auprc": 0.9938809256828479,
      "support": 1000,
      "tp": 945,
      "tn": 6968,
      "fp": 32,
      "fn": 55
    },
    "6": {
      "precision": 0.9733464955577492,
      "recall": 0.986,
      "f1": 0.9796323894684551,
      "specificity": 0.9961428571428571,
      "fpr": 0.003857142857142857,
      "fnr": 0.014,
      "auroc": 0.9996251428571429,
      "auprc": 0.9978358261502657,
      "support": 1000,
      "tp": 986,
      "tn": 6973,
      "fp": 27,
      "fn": 14
    },
    "7": {
      "precision": 0.9558390578999019,
      "recall": 0.974,
      "f1": 0.9648340762753839,
      "specificity": 0.9935714285714285,
      "fpr": 0.0064285714285714285,
      "fnr": 0.026,
      "auroc": 0.9992420000000001,
      "auprc": 0.9951240629668131,
      "support": 1000,
      "tp": 974,
      "tn": 6955,
      "fp": 45,
      "fn": 26
    }
  },
  "confusion_matrix": [
    [
      991,
      0,
      4,
      0,
      4,
      0,
      1,
      0
    ],
    [
      0,
      893,
      54,
      1,
      50,
      0,
      2,
      0
    ],
    [
      1,
      70,
      891,
      0,
      34,
      0,
      4,
      0
    ],
    [
      0,
      0,
      0,
      986,
      0,
      8,
      0,
      6
    ],
    [
      6,
      83,
      94,
      1,
      797,
      0,
      19,
      0
    ],
    [
      0,
      0,
      0,
      17,
      0,
      945,
      0,
      38
    ],
    [
      1,
      1,
      2,
      4,
      2,
      3,
      986,
      1
    ],
    [
      0,
      0,
      0,
      4,
      0,
      21,
      1,
      974
    ]
  ]
}